<manifest alg="2" build="2018.0.0.379" opt="true" iceEnabled="true" iceMarkupVersion="2" iceEnabledOptions="link,responsive,cachebuster,textStyling" exportTarget="other" domain="timlapp.tk" resolutions="1x" timestamp="1516572308241">
  <folder name="css">
    <file name="site_global.css" crc="444006867"/>
    <file name="master_a-master.css" crc="435352445" ref="index:contact"/>
    <file name="index.css" crc="4224995835" ref="index"/>
    <file name="contact.css" crc="3973625392" ref="contact"/>
  </folder>
  <folder name="scripts">
    <file name="jquery-1.8.3.min.js" crc="209076791" ref="index:contact"/>
    <file name="museutils.js" crc="3803043152" ref="index:contact"/>
    <file name="whatinput.js" crc="86476730" ref="index:contact"/>
    <file name="museconfig.js" crc="4153641093" ref="index:contact"/>
    <file name="jquery.watch.js" crc="99325471" ref="index:contact"/>
    <file name="require.js" crc="4157109226" ref="index:contact"/>
  </folder>
  <folder name="images">
    <file name="amsterdam.jpg" crc="4177008286" seo="true" ref="index">
      <caption webpage="index" alt=""/>
    </file>
  </folder>
  <file name="index.html" crc="4239318642" seo="true" mt="1516572270947" redirect="true"/>
  <file name="contact.html" crc="3838818759" seo="true" mt="1516571422899" redirect="true"/>
</manifest>